encomp/__init__.py
encomp/constants.py
encomp/context.py
encomp/conversion.py
encomp/fluids.py
encomp/gases.py
encomp/misc.py
encomp/py.typed
encomp/settings.py
encomp/structures.py
encomp/sympy.py
encomp/thermo.py
encomp/units.py
encomp/utypes.py
encomp/defs/constants.txt
encomp/defs/units.txt
encomp/tests/__init__.py
encomp/tests/conftest.py
encomp/tests/test_builtins.py
encomp/tests/test_constants.py
encomp/tests/test_context.py
encomp/tests/test_conversion.py
encomp/tests/test_examples.py
encomp/tests/test_fluids.py
encomp/tests/test_gases.py
encomp/tests/test_inference.py
encomp/tests/test_misc.py
encomp/tests/test_overloads.py
encomp/tests/test_polars.py
encomp/tests/test_pydantic.py
encomp/tests/test_settings.py
encomp/tests/test_structures.py
encomp/tests/test_sympy.py
encomp/tests/test_thermo.py
encomp/tests/test_transforms.py
encomp/tests/test_transforms_failures.py
encomp/tests/test_units.py
encomp-1.3.10.dist-info/METADATA
encomp-1.3.10.dist-info/WHEEL
encomp-1.3.10.dist-info/licenses/LICENSE
encomp-1.3.10.dist-info/RECORD
