Metadata-Version: 2.4
Name: encomp
Version: 1.3.10
Summary: General-purpose library for engineering calculations
Project-URL: Homepage, https://github.com/wlaur/encomp
Project-URL: Documentation, https://encomp.readthedocs.io
Project-URL: Repository, https://github.com/wlaur/encomp
Project-URL: Issues, https://github.com/wlaur/encomp/issues
Author-email: William Laurén <lauren.william.a@gmail.com>
License: MIT License
License-File: LICENSE
Keywords: calculations,engineering,fluids,physical-quantities,symbolic-math,thermodynamics,units
Classifier: Intended Audience :: Developers
Classifier: Intended Audience :: Science/Research
Classifier: License :: OSI Approved :: MIT License
Classifier: Programming Language :: Python :: 3
Classifier: Programming Language :: Python :: 3.13
Classifier: Topic :: Scientific/Engineering
Classifier: Topic :: Scientific/Engineering :: Physics
Classifier: Topic :: Software Development :: Libraries :: Python Modules
Classifier: Typing :: Typed
Requires-Python: >=3.13
Requires-Dist: asttokens
Requires-Dist: coolprop
Requires-Dist: fire
Requires-Dist: numpy
Requires-Dist: pint>=0.25.2
Requires-Dist: polars
Requires-Dist: pydantic
Requires-Dist: pydantic-settings
Requires-Dist: python-dotenv
Requires-Dist: sympy
Requires-Dist: typeguard
Requires-Dist: typing-extensions
Requires-Dist: uncertainties
Provides-Extra: extra
Requires-Dist: fluids; extra == 'extra'
Requires-Dist: scipy; extra == 'extra'
